lambdata_andrewwhite5/__init__.py
lambdata_andrewwhite5/df_utils.py
lambdata_andrewwhite5-0.0.1.dist-info/LICENSE
lambdata_andrewwhite5-0.0.1.dist-info/METADATA
lambdata_andrewwhite5-0.0.1.dist-info/WHEEL
lambdata_andrewwhite5-0.0.1.dist-info/top_level.txt
lambdata_andrewwhite5-0.0.1.dist-info/RECORD
