Metadata-Version: 2.1
Name: lambdata-andrewwhite5
Version: 0.0.1
Summary: A collection of Data Science helper functions
Home-page: https://github.com/andrewwhite5/lambdata-andrewwhite5
Author: andrewwhite5
License: UNKNOWN
Platform: UNKNOWN
Classifier: Programming Language :: Python :: 3
Classifier: License :: OSI Approved :: MIT License
Classifier: Operating System :: OS Independent
Requires-Python: >3.5
Requires-Dist: numpy
Requires-Dist: pandas
